README.md
setup.py
django_geocode.egg-info/PKG-INFO
django_geocode.egg-info/SOURCES.txt
django_geocode.egg-info/dependency_links.txt
django_geocode.egg-info/pbr.json
django_geocode.egg-info/requires.txt
django_geocode.egg-info/top_level.txt
geocode/__init__.py
geocode/admin.py
geocode/appconfig.py
geocode/conf.py
geocode/helpers.py
geocode/models.py
geocode/signals.py
geocode/tasks.py
geocode/tests.py
geocode/utils.py
geocode/migrations/0001_initial.py
geocode/migrations/__init__.py
geocode/runtests/__init__.py
geocode/runtests/celery_app.py
geocode/runtests/runtests.py
geocode/runtests/settings.py